{"user_idol":{"viewer_id":"98267321","idol_id":"1085","level":"30","exp":"8300","vocal":4300,"dance":3550,"visual":3925,"create_time":"2022-10-14 15:39:53","update_time":"2022-11-21 13:17:30","delete_time":null,"total_param":11775,"idol_info":{"image":"item\/l\/petit_cg\/chara\/1085","idol_id":"1085","idol_name":"\uff78\uff97\uff98\uff7d","short_name":"\uff78\uff97\uff98\uff7d","attribute":"1"},"name":"\uff78\uff97\uff98\uff7d","attribute":"1"},"user_param":{"viewer_id":"98267321","money":"7309832","point":"7719","create_time":"2014-10-30 15:33:55","update_time":"2023-03-29 22:41:41","delete_time":null},"deck_position":3,"idol_message":"\u6559\u4f1a\u306e\u5b50\u4f9b\u305f\u3061\u304c\uff64\u5c06\u6765\u306f\uff71\uff72\uff84\uff9e\uff99\u306b\u306a\u308a\u305f\u3044\u3068\u2026\u3075\u3075\u3063\uff61\u5b09\u3057\u3044\u3088\u3046\u306a\uff64\u56f0\u3063\u305f\u3088\u3046\u306a\u2026","idol_attribute":"1","swf_url":null}